{
    "name": "zombie",
    "type": "dynamic",
    "description": "Replace this string with a description",
    "shape": [
        { "x": -10, "y": 10 },
        { "x": 10, "y": 10 },
        { "x": 10, "y": -10 },
        { "x": -10, "y": -10 }
    ],
    "friction": {
      "collision": 5,
      "linear": 40,
      "rotational": 600
    },
    "sensors": [
        {
            "type": "range",
            "location": { "x": 16, "y": 0 },
            "direction": 0
        }
    ],
    "mass": 1,    
    "controller": "lib/zombie.so"
}